wikipedia_tools/.gitignore
wikipedia_tools/__init__.py
wikipedia_tools/test.ipynb
wikipedia_tools/analyzer/__init__.py
wikipedia_tools/analyzer/feature_extractor.py
wikipedia_tools/analyzer/numbers_over_time.py
wikipedia_tools/analyzer/revisions.py
wikipedia_tools/base/wikipedia_w_time/__init__.py
wikipedia_tools/base/wikipedia_w_time/exceptions.py
wikipedia_tools/base/wikipedia_w_time/util.py
wikipedia_tools/base/wikipedia_w_time/wikipedia.py
wikipedia_tools/processor/__init__.py
wikipedia_tools/processor/loader.py
wikipedia_tools/processor/processor.py
wikipedia_tools/scraper/__init__.py
wikipedia_tools/scraper/category_extractor.py
wikipedia_tools/scraper/downloader.py
wikipedia_tools/scraper/revision_extractor.py
wikipedia_tools/scraper/wikipedia_parser.py
wikipedia_tools/scraper/wikirevparser_with_time.py
wikipedia_tools/utils/__init__.py
wikipedia_tools/utils/properties.py
wikipedia_tools/utils/utils.py
wikipedia_tools-2.4.1.dist-info/LICENSE
wikipedia_tools-2.4.1.dist-info/WHEEL
wikipedia_tools-2.4.1.dist-info/METADATA
wikipedia_tools-2.4.1.dist-info/RECORD
