Metadata-Version: 2.1
Name: wikipedia_tools
Version: 2.4.1
Summary: This is a Wikipedia Tool to fetch revisions based on a period of time.
Keywords: wikipedia,wikipedia revisions,wikipedia stats
Author-email: Roxanne El Baff <roxanne.elbaff@dlr.de>
Requires-Python: >=3.7
Requires-Dist: pandas>=1.0.1
Requires-Dist: matplotlib>=3.2.1
Requires-Dist: pymediawiki==0.7.2
Requires-Dist: IPy>=1.01
Requires-Dist: seaborn>=0.11.2
Requires-Dist: nlpaf>1.0.0; python_version <= "3.8"
Requires-Dist: tqdm==4.43.0
Requires-Dist: dataclasses==0.6
Requires-Dist: beautifulsoup4
Requires-Dist: requests>=2.0.0,<3.0.0
Requires-Dist: pip-tools ; extra == "dev"
Project-URL: Homepage, https://github.com/DLR-SC/wikipedia-periodic-revisions
Provides-Extra: dev
